lindu/LMain.py
lindu/__init__.py
lindu/Widgets/__init__.py
lindu/Widgets/Displays/LSeismoView.py
lindu/Widgets/Displays/MplCanvas.py
lindu/Widgets/Displays/__init__.py
lindu/Widgets/Help/__init__.py
lindu/Widgets/Help/About/About.py
lindu/Widgets/Help/About/__init__.py
lindu/Widgets/Images/icon/main_logo.png
lindu/Widgets/Images/larges/spl_scr.png
lindu/Widgets/LTomography/__init__.py
lindu/Widgets/LTomography/LT2D/LTomo2D.py
lindu/Widgets/LTomography/LT2D/__init__.py
lindu/Widgets/LTomography/LT3D/LTomo3D.py
lindu/Widgets/LTomography/LT3D/__init__.py
lindu/Widgets/Settings/LStyle.py
lindu/Widgets/Settings/LStyle.qss
lindu/Widgets/Settings/__init__.py
lindu/Widgets/ui/About.ui
lindu/Widgets/ui/LMain.ui
lindu/Widgets/ui/LSeismoView.ui
lindu/Widgets/ui/LTomo2D.ui
lindu/Widgets/ui/LTomo3D.ui
lindu-0.0.1.dist-info/LICENSE.md
lindu-0.0.1.dist-info/METADATA
lindu-0.0.1.dist-info/WHEEL
lindu-0.0.1.dist-info/top_level.txt
lindu-0.0.1.dist-info/RECORD
