Metadata-Version: 2.1
Name: lindu
Version: 0.0.1
Summary: a library and GUI for earthquake data processing
Home-page: https://github.com/comp-geoph-itera/lindu-software/tree/package
Author: Yudha Styawan
Author-email: yudhastyawan@gmail.com
License: UNKNOWN
Project-URL: Bug Tracker, https://github.com/comp-geoph-itera/lindu-software/issues
Project-URL: Documentation, https://github.com/comp-geoph-itera/lindu-software/tree/package
Platform: UNKNOWN
Classifier: Programming Language :: Python :: 3
Classifier: License :: OSI Approved :: GNU General Public License v3 (GPLv3)
Requires-Python: >=3.8
License-File: LICENSE.md
Requires-Dist: PySide2
Requires-Dist: yubundle
Requires-Dist: obspy
